Metadata-Version: 2.1
Name: pytest-docstyle
Version: 2.0.0
Summary: pytest plugin to run pydocstyle
Home-page: https://github.com/henry0312/pytest-docstyle
Author: OMOTO Tsukasa
Author-email: tsukasa@oomo.to
License: MIT
Platform: UNKNOWN
Classifier: Development Status :: 3 - Alpha
Classifier: Intended Audience :: Developers
Classifier: Topic :: Software Development :: Testing
Classifier: License :: OSI Approved :: MIT License
Classifier: Framework :: Pytest
Classifier: Programming Language :: Python :: 3
Classifier: Programming Language :: Python :: 3.5
Classifier: Programming Language :: Python :: 3.6
Classifier: Programming Language :: Python :: 3.7
Classifier: Programming Language :: Python :: 3.8
Requires-Python: ~=3.5
Provides-Extra: tests
